COPYING.txt
MANIFEST.in
README.rst
setup.cfg
setup.py
glerbl/__init__.py
glerbl/__main__.py
glerbl.egg-info/PKG-INFO
glerbl.egg-info/SOURCES.txt
glerbl.egg-info/dependency_links.txt
glerbl.egg-info/entry_points.txt
glerbl.egg-info/requires.txt
glerbl.egg-info/top_level.txt
glerbl/check/__init__.py
glerbl/check/no_before_commit.py
glerbl/check/no_non_ascii_filenames.py
glerbl/check/no_trailing_whitespace.py
glerbl/check/python_no_trailing_semicolon.py
glerbl/check/python_pep8.py