Metadata-Version: 1.1
Name: glerbl
Version: 0.1.0
Summary: Glerbl manages git hooks.
Home-page: https://github.com/lddubeau/glerbl
Author: Louis-Dominique Dubeau
Author-email: ldd@lddubeau.com
License: GPLv3+
Keywords: git,git hooks
Platform: UNKNOWN
Classifier: Programming Language :: Python :: 2.7
Classifier: Programming Language :: Python :: 3
Classifier: Development Status :: 4 - Beta
Classifier: Environment :: Console
Classifier: Intended Audience :: Developers
Classifier: License :: OSI Approved :: GNU General Public License v3 or later (GPLv3+)
Classifier: Operating System :: POSIX
Classifier: Topic :: Software Development :: Version Control
Classifier: Topic :: Software Development :: Quality Assurance
